README.md
setup.py
github/__init__.py
python_github.egg-info/PKG-INFO
python_github.egg-info/SOURCES.txt
python_github.egg-info/dependency_links.txt
python_github.egg-info/requires.txt
python_github.egg-info/top_level.txt
tests/__init__.py
tests/test_github.py