Metadata-Version: 1.1
Name: python-github
Version: 0.1.0.dev0
Summary: GitHub API Wrapper with super powers
Home-page: https://githubapi.com/biwin/github
Author: Biwin John
Author-email: biwinjohn@gmail.com
License: Apache 2.0
Download-URL: https://githubapi.com/biwin/github/
Keywords: github-api,github,python
Platform: UNKNOWN
Classifier: Programming Language :: Python
Classifier: Programming Language :: Python :: 2
Classifier: Programming Language :: Python :: 3
